tiller/__init__.py
tiller/__main__.py
tiller-0.1.0.dist-info/METADATA
tiller-0.1.0.dist-info/WHEEL
tiller-0.1.0.dist-info/entry_points.txt
tiller-0.1.0.dist-info/top_level.txt
tiller-0.1.0.dist-info/RECORD
