Metadata-Version: 2.1
Name: tiller
Version: 0.1.0
Summary: A small example sailboat plugin.
Home-page: https://github.com/cole-wilson/tiller
Author: Cole Wilson
Author-email: cole@colewilson.xyz
License: none
Platform: UNKNOWN
Classifier: Programming Language :: Python :: 3
Requires-Python: >=3.6
Requires-Dist: sailboat
